alibabacloud_ens20171110/__init__.py
alibabacloud_ens20171110/client.py
alibabacloud_ens20171110/models/__init__.py
alibabacloud_ens20171110/models/_accosicate_network_acl_request.py
alibabacloud_ens20171110/models/_accosicate_network_acl_response.py
alibabacloud_ens20171110/models/_accosicate_network_acl_response_body.py
alibabacloud_ens20171110/models/_add_backend_servers_request.py
alibabacloud_ens20171110/models/_add_backend_servers_response.py
alibabacloud_ens20171110/models/_add_backend_servers_response_body.py
alibabacloud_ens20171110/models/_add_backend_servers_shrink_request.py
alibabacloud_ens20171110/models/_add_network_interface_to_instance_request.py
alibabacloud_ens20171110/models/_add_network_interface_to_instance_response.py
alibabacloud_ens20171110/models/_add_network_interface_to_instance_response_body.py
alibabacloud_ens20171110/models/_add_snat_ip_for_snat_entry_request.py
alibabacloud_ens20171110/models/_add_snat_ip_for_snat_entry_response.py
alibabacloud_ens20171110/models/_add_snat_ip_for_snat_entry_response_body.py
alibabacloud_ens20171110/models/_assign_private_ip_addresses_request.py
alibabacloud_ens20171110/models/_assign_private_ip_addresses_response.py
alibabacloud_ens20171110/models/_assign_private_ip_addresses_response_body.py
alibabacloud_ens20171110/models/_associate_ens_eip_address_request.py
alibabacloud_ens20171110/models/_associate_ens_eip_address_response.py
alibabacloud_ens20171110/models/_associate_ens_eip_address_response_body.py
alibabacloud_ens20171110/models/_associate_ha_vip_request.py
alibabacloud_ens20171110/models/_associate_ha_vip_response.py
alibabacloud_ens20171110/models/_associate_ha_vip_response_body.py
alibabacloud_ens20171110/models/_attach_disk_request.py
alibabacloud_ens20171110/models/_attach_disk_response.py
alibabacloud_ens20171110/models/_attach_disk_response_body.py
alibabacloud_ens20171110/models/_attach_ens_instances_request.py
alibabacloud_ens20171110/models/_attach_ens_instances_response.py
alibabacloud_ens20171110-10.0.2.dist-info/LICENSE
alibabacloud_ens20171110-10.0.2.dist-info/METADATA
alibabacloud_ens20171110-10.0.2.dist-info/WHEEL
alibabacloud_ens20171110-10.0.2.dist-info/top_level.txt
alibabacloud_ens20171110-10.0.2.dist-info/RECORD
